{
  "groups": [
    {
      "group_name": "nA!",
      "group_description": {
        "zh": "nA!"
      },
      "voice_list": [
        {
          "name": "nA",
          "path": "1nA/NA.mp3",
          "description": {
            "zh": "nA",
            "ja": "nA",
            "en": "nA",
            "Romaji": ""
          }
        },
        {
          "name": "nA↑",
          "path": "1nA/NA_.mp3",
          "description": {
            "zh": "nA↑",
            "ja": "nA↑",
            "en": "nA↑",
            "Romaji": ""
          }
        }
      ]
    },
    {
      "group_name": "台词回",
      "group_description": {
        "zh": "台词回"
      },
      "voice_list": [
        {
          "name": "kimo",
          "path": "3dialogue/kimo.mp3",
          "description": {
            "zh": "kimo",
            "ja": "kimo",
            "en": "kimo",
            "Romaji": ""
          }
        },
        {
          "name": "いっぺん…死んでみる？",
          "path": "3dialogue/changshisiyici.mp3",
          "description": {
            "zh": "いっぺん…死んでみる？",
            "ja": "いっぺん…死んでみる？",
            "en": "いっぺん…死んでみる？",
            "Romaji": ""
          }
        },
        {
          "name": "o泡",
          "path": "3dialogue/Opao.mp3",
          "description": {
            "zh": "o泡果奶",
            "ja": "o泡果奶",
            "en": "o泡果奶",
            "Romaji": ""
          }
        },
        {
          "name": "你们的心就由Imi收下啦",
          "path": "3dialogue/shouxiale.mp3",
          "description": {
            "zh": "你们的心就由Imi收下啦",
            "ja": "你们的心就由Imi收下啦",
            "en": "你们的心就由Imi收下啦",
            "Romaji": ""
          }
        },
        {
          "name": "可爱又迷人的正面角色",
          "path": "3dialogue/keaimirenzhengmianjuese.mp3",
          "description": {
            "zh": "Imi是可爱又迷人的正面角色",
            "ja": "Imi是可爱又迷人的正面角色",
            "en": "Imi是可爱又迷人的正面角色",
            "Romaji": ""
          }
        },
        {
          "name": "什么时候来哄哄Imi呀",
          "path": "3dialogue/honghongimi.mp3",
          "description": {
            "zh": "什么时候来哄哄Imi呀",
            "ja": "什么时候来哄哄Imi呀",
            "en": "什么时候来哄哄Imi呀",
            "Romaji": ""
          }
        },
        {
          "name": "哄完别人能来哄哄Imi吗",
          "path": "3dialogue/hongwanbierennenglaihonghongimima.mp3",
          "description": {
            "zh": "该哄Imi了",
            "ja": "该哄Imi了",
            "en": "该哄Imi了",
            "Romaji": ""
          }
        },
        {
          "name": "好过分啊",
          "path": "3dialogue/haoguofena.mp3",
          "description": {
            "zh": "好过分啊",
            "ja": "好过分啊",
            "en": "好过分啊",
            "Romaji": ""
          }
        },
        {
          "name": "啊——",
          "path": "3dialogue/aaa.mp3",
          "description": {
            "zh": "啊——",
            "ja": "啊——",
            "en": "啊——",
            "Romaji": ""
          }
        }
      ]
    },
    {
      "group_name": "不可以休息噢",
      "group_description": {
        "zh": "不可以休息噢"
      },
      "voice_list": [
        {
          "name": "你的微积分还没写完...",
          "path": "2CantRest/calculus.mp3",
          "description": {
            "zh": "你的微积分还没写完..."
          }
        },
        {
          "name": "你的作业还没写完...",
          "path": "2CantRest/hw.mp3",
          "description": {
            "zh": "你的作业还没写完..."
          }
        },
        {
          "name": "你的论文还没写完...",
          "path": "2CantRest/paper_zh.mp3",
          "description": {
            "zh": "你的论文还没写完..."
          }
        },
        {
          "name": "你的paper还没写完...",
          "path": "2CantRest/paper.mp3",
          "description": {
            "zh": "你的paper还没写完..."
          }
        },
        {
          "name": "你的bug还没改完...",
          "path": "2CantRest/bug.mp3",
          "description": {
            "zh": "你的bug还没改完..."
          }
        },
        {
          "name": "你的代码又报错了...",
          "path": "2CantRest/segfault.mp3",
          "description": {
            "zh": "你的代码又报错了..."
          }
        },
        {
          "name": "你的稿子还没画好...",
          "path": "2CantRest/drawing.mp3",
          "description": {
            "zh": "你的稿子还没画好..."
          }
        }
      ]
    },
    {
      "group_name": "其他",
      "group_description": {
        "zh": "其他"
      },
      "voice_list": [
        {
          "name": "你打我",
          "path": "4others/nidawo.mp3",
          "description": {
            "zh": "你打我",
            "ja": "你打我",
            "en": "你打我",
            "Romaji": ""
          }
        }
      ]
    }
  ]
}
